coimealta/__init__.py
coimealta/contacts/README.md
coimealta/contacts/__init__.py
coimealta/contacts/contact
coimealta/contacts/contacts_data.py
coimealta/contacts/csv-contacts.el
coimealta/contacts/format_address_labels.py
coimealta/contacts/link_contacts.py
coimealta/contacts/list_contacts.py
coimealta/contacts/people.py
coimealta/inventory/ChangeLog.md
coimealta/inventory/LICENSE
coimealta/inventory/README.md
coimealta/inventory/Setup.hs
coimealta/inventory/Storage.hs
coimealta/inventory/__init__.py
coimealta/inventory/books.py
coimealta/inventory/cabal.sandbox.config
coimealta/inventory/perishables.py
coimealta/inventory/runstorageserver
coimealta/inventory/storage
coimealta/inventory/storage-client
coimealta/inventory/storage.cabal
coimealta/inventory/storage.el
coimealta/inventory/storage.py
coimealta/inventory/storage.yaml
coimealta/inventory/storage_client.py
coimealta-0.0.14.dist-info/LICENSE
coimealta-0.0.14.dist-info/WHEEL
coimealta-0.0.14.dist-info/METADATA
coimealta-0.0.14.dist-info/RECORD
