Metadata-Version: 2.1
Name: coimealta
Version: 0.0.14
Summary: Contacts and inventory tracker
Author-email: "John C. G. Sturdy" <jcg.sturdy@gmail.com>
Classifier: License :: OSI Approved :: GNU General Public License v3 or later (GPLv3+)
Requires-Dist: python-decouple
